{
  "gate": [
    {"order": 1, "id": "gate", "host": "127.0.0.1", "clientPort": "#GateClientPort#", "port":  "#GatePort#", "frontend": true,"db": "logDB"}
  ],
  "connector": [
    {"order": 1, "id": "connector-s1",   "host": "127.0.0.1", "port": "#ConnectorPort#", "clientHost": "#ConnectorClientHost#", "clientPort": "#ConnectorClientPort#", "frontend": true, "max-connections": 5000, "db": "db"}
  ],
  "world": [
    {"order": 1, "id": "world",   "host": "127.0.0.1", "port": "#WorldPort#", "db": "db"}
  ],
  "area": [
    {"order": 1, "id": "area-s1",   "host": "127.0.0.1", "port": "#AreaPort#", "db": "db","allOrder":"[1]"}
  ],
  "war": [
    {"order": 1, "id": "war-s1",   "host": "1270.0.0.1", "port": 4851, "clientHost": "#WarClientHost#", "clientPort": "#WarClientPort#", "frontend": true, "max-connections": 5000, "db": "db"}
  ]

}